MANIFEST.in
README.rst
requirements.txt
setup.py
ajcli.egg-info/PKG-INFO
ajcli.egg-info/SOURCES.txt
ajcli.egg-info/dependency_links.txt
ajcli.egg-info/entry_points.txt
ajcli.egg-info/requires.txt
ajcli.egg-info/top_level.txt
jira/__init__.py
jira/__main__.py
jira/cli.py
jira/factory.py
jira/model.py
jira/service.py
jira/util.py