Metadata-Version: 1.0
Name: ajcli
Version: 0.1.2
Summary: another jira interface including cli
Home-page: https://bitbucket.org/afriemann/jiracli
Author: Aljosha Friemann
Author-email: aljosha.friemann@gmail.com
License: UNKNOWN
Keywords: cli,jira,development
Platform: UNKNOWN
